LICENSE
README.md
setup.py
JanexLogin/__init__.py
JanexLogin/jsonfunctions.py
JanexLogin/main.py
JanexLogin.egg-info/PKG-INFO
JanexLogin.egg-info/SOURCES.txt
JanexLogin.egg-info/dependency_links.txt
JanexLogin.egg-info/top_level.txt