Metadata-Version: 2.1
Name: JanexLogin
Version: 0.0.2
Summary: A Python library for creating login systems
Home-page: https://github.com/ChronoByte404/JanexLogin
Author: Brendon Campbell
Author-email: info@timewiserobot.com
License: Lily License 3.0 - Commercial Edition
Classifier: Programming Language :: Python :: 3
Classifier: Operating System :: OS Independent
Requires-Python: >=3.6
License-File: LICENSE
